pacifica_sdk/__init__.py
pacifica_sdk/constants.py
pacifica_sdk/enums.py
pacifica_sdk/async_/__init__.py
pacifica_sdk/async_/api.py
pacifica_sdk/async_/client.py
pacifica_sdk/async_/exchange.py
pacifica_sdk/async_/info.py
pacifica_sdk/async_/websocket_manager.py
pacifica_sdk/models/__init__.py
pacifica_sdk/models/requests.py
pacifica_sdk/models/responses.py
pacifica_sdk/models/ws_stream.py
pacifica_sdk/models/ws_subscribe.py
pacifica_sdk/sync/__init__.py
pacifica_sdk/sync/base.py
pacifica_sdk/sync/client.py
pacifica_sdk/sync/exchange.py
pacifica_sdk/sync/info.py
pacifica_sdk/sync/websocket_manager.py
pacifica_sdk/utils/__init__.py
pacifica_sdk/utils/error.py
pacifica_sdk/utils/signing.py
pacifica_sdk/utils/tools.py
pacifica_sdk-0.1.0.dist-info/METADATA
pacifica_sdk-0.1.0.dist-info/WHEEL
pacifica_sdk-0.1.0.dist-info/top_level.txt
pacifica_sdk-0.1.0.dist-info/RECORD
