Metadata-Version: 2.4
Name: pacifica-sdk
Version: 0.1.0
Summary: Python Pacifica Exchange SDK
Author: HedgeHog
License: MIT
Requires-Python: >=3.10
Requires-Dist: aiohttp<4.0,>=3.9
Requires-Dist: requests<3.0,>=2.31
Requires-Dist: pydantic<3.0,>=2.0
Requires-Dist: orjson<4.0,>=3.8
Requires-Dist: base58>=2.1
Requires-Dist: solders>=0.26
